{
  "COLUMNS": [
    "YEAR",
    "COUNTDATE",
    "FISHCOUNT",
    "SPECIESID",
    "COUNTLOCATIONID",
    "COUNTLOCATION",
    "SPECIES"
  ],
  "DATA": [
    [
      2025,
      "August, 01 2025 00:00:00",
      3,
      430,
      27,
      "Dog Salmon River",
      "Coho"
    ],
    [
      2025,
      "August, 02 2025 00:00:00",
      2,
      430,
      27,
      "Dog Salmon River",
      "Coho"
    ],
    [
      2025,
      "August, 03 2025 00:00:00",
      1,
      430,
      27,
      "Dog Salmon River",
      "Coho"
    ],
    [
      2025,
      "August, 04 2025 00:00:00",
      2,
      430,
      27,
      "Dog Salmon River",
      "Coho"
    ],
    [
      2025,
      "August, 05 2025 00:00:00",
      13,
      430,
      27,
      "Dog Salmon River",
      "Coho"
    ],
    [
      2025,
      "August, 06 2025 00:00:00",
      100,
      430,
      27,
      "Dog Salmon River",
      "Coho"
    ],
    [
      2025,
      "July, 25 2025 00:00:00",
      1,
      430,
      27,
      "Dog Salmon River",
      "Coho"
    ],
    [
      2025,
      "July, 26 2025 00:00:00",
      0,
      430,
      27,
      "Dog Salmon River",
      "Coho"
    ],
    [
      2025,
      "July, 27 2025 00:00:00",
      0,
      430,
      27,
      "Dog Salmon River",
      "Coho"
    ],
    [
      2025,
      "July, 28 2025 00:00:00",
      0,
      430,
      27,
      "Dog Salmon River",
      "Coho"
    ],
    [
      2025,
      "July, 29 2025 00:00:00",
      0,
      430,
      27,
      "Dog Salmon River",
      "Coho"
    ],
    [
      2025,
      "July, 30 2025 00:00:00",
      0,
      430,
      27,
      "Dog Salmon River",
      "Coho"
    ],
    [
      2025,
      "July, 31 2025 00:00:00",
      1,
      430,
      27,
      "Dog Salmon River",
      "Coho"
    ]
  ],
  "metadata": {
    "last_downloaded": "2025-08-11T12:34:07.591347",
    "download_source": "ADFG Fish Counts API",
    "location_id": 27,
    "species_id": 430,
    "year": 2025,
    "location_name": "Dog Salmon River",
    "species_name": "Coho Salmon",
    "total_records": 13,
    "data_range": {
      "start_date": "July, 25 2025 00:00:00",
      "end_date": "August, 06 2025 00:00:00"
    },
    "totalRecords": 13,
    "totalCount": 123,
    "daysWithData": 8,
    "latestDate": 2025,
    "lastUpdated": "2025-08-12T11:38:23.215111",
    "updateCount": 1,
    "mergeHistory": [
      {
        "timestamp": "2025-08-12T11:38:23.215113",
        "newRecords": 0,
        "updatedRecords": 0,
        "unchangedRecords": 13,
        "totalRecords": 13
      }
    ]
  },
  "record_update_times": {},
  "merge_info": {
    "new_records_added": 0,
    "existing_records_updated": 0,
    "unchanged_records": 13,
    "total_records": 13,
    "merge_timestamp": "2025-08-12T11:38:23.215118",
    "data_freshness": {
      "latest_date": 2025,
      "days_with_data": 8,
      "total_count": 123,
      "total_records": 13
    }
  }
}